fastapi_storage_helper/__init__.py
fastapi_storage_helper/storage.py
fastapi_storage_helper-0.0.11.dist-info/METADATA
fastapi_storage_helper-0.0.11.dist-info/WHEEL
fastapi_storage_helper-0.0.11.dist-info/RECORD
