Metadata-Version: 2.3
Name: fastapi_storage_helper
Version: 0.0.11
Summary: FastAPI Storage Helper
Project-URL: Homepage, https://github.com/megatron-global/fastapi-queue
Project-URL: Bug Tracker, https://github.com/megatron-global/fastapi-queue/issues
Author-email: Dzung Nguyen <dung@megatron-solutions.com>
Classifier: License :: OSI Approved :: MIT License
Classifier: Operating System :: OS Independent
Classifier: Programming Language :: Python :: 3
Requires-Python: >=3.10
Requires-Dist: boto3>=1.26.7
Requires-Dist: boto>=2.49.0
Requires-Dist: botocore>=1.29.22
